[
    {
        "id": "Audifonos-E50",
        "titulo": "Audífonos E50",
        "imagen": ["./images/audifonos/1.jpg","./images/audifonos/1.1.jpg","./images/audifonos/1.2.jpg"],
        "categoria": {
            "nombre": "Audífonos",
            "id": "electronico"
        },
        "precio": 55000,
        "colores": ["negros"],
        "info": "Audífonos E50 $55.000 Bluetooth 5.1 estéreo Sensor digital Estilo: en la oreja Principio de vocalismo: Díamica Origen: China continental Botón de Control: Sí Comunicación: inalámbrica Control de volumen: Sí Tipo de enchufe: Tipo de línea Material de las almohadillas para auriculares: Silicona Tipo inalámbrico: Bluetooth Longitud de línea: 0 m Lista de paquetes: Cable de carga, Estuche de carga, Manual del usuario Códecs: ac Diámetro del conductor: 10 mm Resistencia: 32 Sensibilidad: 128dB Es inalámbrico: Sí Conectores: usb Tipo de auriculares: Semi-abierto Versión de Bluetooth: 5.1 Distorsión armónica Total: 1% Método de carga: Estuche de carga Salida máxima: 1mW Aplicación de soporte: No Función: deportes, para teléfono móvil, para videojuegos, auriculares comunes Luces led, Duración batería auriculares = 3.5 H Duración batería caja = 3 cargas + Contesta llamadas, Con Micrófono: Sí Características: cancelación de ruido activa, resistente al agua salpicaduras. No sumergir en líquidos",
        "numerodecantidades": 10,
        "tallaInicial":  37,
        "tallaFinal": 43
        
    }
    ,

    {
        "id": "zandalias-01",
        "titulo": "Puma",
        "imagen": ["./images/zandalias/2.jpg","./images/zandalias/2.1.jpg","./images/zandalias/2.2.jpg"],
        "categoria": {
            "nombre": "zandalias",
            "id": "calzado"
        },
        "precio":80000,
        "colores": ["negros", "vintage", "blanco"],
        "info" : "Dama : Tallas 35 a la 40,  Precio 88.000 pesos ",
        "numerodecantidades": 10,
        "tallaInicial":  35,
        "tallaFinal": 40
    },
    {
        "id": "zandalias-02",
        "titulo": "zandalias planas - niña",
        "imagen": ["./images/zandalias/3.jpg","./images/zandalias/3.1.jpg","./images/zandalias/3.2.jpg" ,"./images/zandalias/4.jpg"],
        "categoria": {
            "nombre": "zandalias",
            "id": "calzado"
        },
        "precio":20000,
        "colores": ["vintage", "rosadas"],
        "info" : "📍Sandalias planas☝ 📍Niñas: Tallas 27 a la 33👣 , Precio 20.000 pesos 💵",
        "numerodecantidades": 10,
        "tallaInicial":  27,
        "tallaFinal": 33,
        "tipos" : ["barbie", "stich"] 
    },
    {
        "id": "zapatillas-01",
        "titulo": "HUGO BOSS",
        "imagen": ["./images/zapatillas/1.jpg","./images/zapatillas/1.1.jpg"],
        "categoria": {
            "nombre": "zapatillas",
            "id": "calzado"
        },
        "precio":115000,
        "colores": ["negros"],
        "info" : "▪Talla 37 al 43👣,  ▪ Precio: 115.000 pesos 💸,   ▪ Pegado Vulcanizado🤩 ",
        "numerodecantidades": 10,
        "tallaInicial":  37,
        "tallaFinal": 43
    },

    {
        "id": "zapatillas-02",
        "titulo": "HUGO BOSS",
        "imagen":["./images/zapatillas/2.jpg","./images/zapatillas/2.1.jpg"],
        "categoria": {
            "nombre": "zapatillas",
            "id": "calzado"
        },
        "precio": 115000,
        "colores": ["negros"],
        "info" : "▪Talla 37 al 43👣,  ▪ Precio: 115.000 pesos 💸,   ▪ Pegado Vulcanizado🤩 ",
        "numerodecantidades": 10,
        "tallaInicial":  37,
        "tallaFinal": 43
    },

    {
        "id": "zapatillas-03",
        "titulo": "HUGO BOSS",
        "imagen":["./images/zapatillas/3.jpg","./images/zapatillas/3.1.jpg"],
        "categoria": {
            "nombre": "zapatillas",
            "id": "calzado"
        },
        "precio":115000,
        "colores": ["negros"],
        "info" : "▪Talla 37 al 43👣,  ▪ Precio: 115.000 pesos 💸,   ▪ Pegado Vulcanizado🤩 ",
        "numerodecantidades": 10,
        "tallaInicial":  37,
        "tallaFinal": 43
    },
    {
        "id": "zapatillas-04",
        "titulo": "HUGO BOSS",
        "imagen":["./images/zapatillas/4.jpg","./images/zapatillas/4.1.jpg","./images/zapatillas/4.2.jpg" ],
        "categoria": {
            "nombre": "zapatillas",
            "id": "calzado"
        },
        "precio": 128000,
        "colores": ["negros"],
        "info" : "Dama y Caballero: Tallas 37 a la 43👣 , Precio: 128.000 pesos 💵",
        "numerodecantidades": 10,
        "tallaInicial":  37,
        "tallaFinal": 43 
    },
    {
        "id": "zapatillas-05",
        "titulo": "Adidas",
        "imagen":["./images/zapatillas/14.jpg","./images/zapatillas/14.1.jpg"],
        "categoria": {
            "nombre": "Adidas",
            "id": "calzado"
        },
        "precio": 45000,
        "colores": ["negro con blanco y naranja"],
        "info" : "📍Adidas☝ 📍Dama y Caballero, Tallas: 35 a la 43👣, Precio: 45.000 pesos 💵",
        "numerodecantidades": 10,
        "tallaInicial":  35,
        "tallaFinal": 43 
    },
    {
        "id": "zapatillas-06",
        "titulo": "JORDAN RETRO 1",
        "imagen":["./images/zapatillas/13.jpg","./images/zapatillas/13.1.jpg"],
        "categoria": {
            "nombre": "JORDAN RETRO 1",
            "id": "calzado"
        },
        "precio": 95000,
        "colores": ["negro con blanco "],
        "info" : "🍯 JORDAN RETRO 1 🍯 Todas Las Tallas Disponibles Para Dama &  Caballero㊙ ",
        "numerodecantidades": 10,
        "tallaInicial":  36,
        "tallaFinal": 43 
    },
    {
        "id": "zapatillas-07",
        "titulo": " JORDAN RETRO 1 PARIS",
        "imagen":["./images/zapatillas/12.jpg"],
        "categoria": {
            "nombre": " JORDAN RETRO 1 PARIS",
            "id": "calzado"
        },
        "precio": 95000,
        "colores": ["blanco con gris "],
        "info" : "🍯 JORDAN RETRO 1 PARIS 🍯 Todas Las Tallas Disponibles Para Dama &  Caballero㊙ ",
        "numerodecantidades": 10,
        "tallaInicial":  36,
        "tallaFinal": 43 
    },
    {
        "id": "zapatillas-08",
        "titulo": " Dolce & Gabanna Dama🍒",
        "imagen":["./images/zapatillas/11.jpg"],
        "categoria": {
            "nombre": "Dolce & Gabanna Dama",
            "id": "calzado"
        },
        "precio": 155000,
        "colores": ["blanco con negro "],
        "info" : "Dolce & Gabanna Dama  calzado: mujeres",
        "numerodecantidades": 10,
        "tallaInicial":  36,
        "tallaFinal": 40 
    },
    {
        "id": "zapatillas-09",
        "titulo": " Dolce & Gabanna Dama🍒",
        "imagen":["./images/zapatillas/10.jpg"],
        "categoria": {
            "nombre": "Dolce & Gabanna Dama",
            "id": "calzado"
        },
        "precio": 155000,
        "colores": ["blanco con tonos rojos "],
        "info" : "Dolce & Gabanna Dama  calzado: mujeres",
        "numerodecantidades": 10,
        "tallaInicial":  36,
        "tallaFinal": 40 
    },
    {
        "id": "zapatillas-11",
        "titulo": " Dolce & Gabanna Dama🍒",
        "imagen":["./images/zapatillas/9.jpg"],
        "categoria": {
            "nombre": "Dolce & Gabanna Dama",
            "id": "calzado"
        },
        "precio": 155000,
        "colores": ["blanco con negro y rojo con detalles de dorado "],
        "info" : "Dolce & Gabanna Dama  calzado: mujeres, blanco con negro y rojo con detalles de dorado",
        "numerodecantidades": 10,
        "tallaInicial":  36,
        "tallaFinal": 40 
    },
    {
        "id": "zapatillas-12",
        "titulo": " Dolce & Gabanna Dama🍒",
        "imagen":["./images/zapatillas/8.jpg", "./images/zapatillas/8.1.jpg"],
        "categoria": {
            "nombre": "Dolce & Gabanna Dama",
            "id": "calzado"
        },
        "precio": 155000,
        "colores": ["blanco con dorado con la palabra love"],
        "info" : "Dolce & Gabanna Dama  calzado: mujeres, blanco con dorado con la palabra love",
        "numerodecantidades": 10,
        "tallaInicial":  36,
        "tallaFinal": 40 
    },

    {
        "id": "zapatillas-13",
        "titulo": " Nike mercurial Air zoom",
        "imagen":["./images/zapatillas/7.jpg"],
        "categoria": {
            "nombre":  "Nike mercurial Air zoom",
            "id": "calzado"
        },
        "precio": 165000,
        "colores": ["naranja con negro y figuras"],
        "info" : "Nike mercurial Air zoom para dama y hombre ",
        "numerodecantidades": 10,
        "tallaInicial":  36,
        "tallaFinal": 45 
    },

    
    {
        "id": "zapatillas-14",
        "titulo": " Nike mercurial Air zoom",
        "imagen":["./images/zapatillas/6.jpg"],
        "categoria": {
            "nombre":  "Nike mercurial Air zoom",
            "id": "calzado"
        },
        "precio": 165000,
        "colores": ["color azul aguamarina con tonos morados y blancos"],
        "info" : "Nike mercurial Air zoom para dama y hombre ",
        "numerodecantidades": 10,
        "tallaInicial":  36,
        "tallaFinal": 45 
    },
    {
        "id": "zapatillas-15",
        "titulo": " Nike tiempo aluminio",
        "imagen":["./images/zapatillas/5.jpg", "./images/zapatillas/5.1.jpg", "./images/zapatillas/5.2jpg"],
        "categoria": {
            "nombre":  "Nike tiempo aluminio",
            "id": "calzado"
        },
        "precio": 195000,
        "colores": ["logo de nike de blanco con cafe", "logo de nike verde con rosa" , "logo de nike negro con negro"],
        "info" : "Nike tiempo aluminio ",
        "numerodecantidades": 10,
        "tallaInicial":  40,
        "tallaFinal": 45 
    },
    {
        "id": "audifonos-03",
        "titulo": " AIRPODS MAX",
        "imagen":["./images/audifonos/2.jpg", "./images/audifonos/2.1.jpg", "./images/audifonos/2.3.jpg", "./images/audifonos/2.4.jpg", "./images/audifonos/2.5.jpg", "./images/audifonos/2.6.jpg", "./images/audifonos/2.7.jpg", "./images/audifonos/2.8.jpg", "./images/audifonos/2.9.jpg", "./images/audifonos/2.9.1.jpg","./images/audifonos/2.9.2.jpg", "./images/audifonos/2.9.3.jpg", "./images/audifonos/2.9.4.jpg","./images/audifonos/2.9.5.jpg", "./images/audifonos/2.9.6.jpg"],
        "categoria": {
            "nombre":  "AIRPODS MAX",
            "id": "electronico"
        },
        "precio": 95000,
        "colores": ["dorado con tonos blnacos  ", "blanco con  tonos dorados  ", "color negro  ", "color rojo  ", "color gris  ", "color rojo con tonos rojos suaves", "  color azul plateado", "  color azul plateado, con tonos de azul/aguamarina", "  color verde", "  color blanco"],
        "info" : "Réplica 1.1 De Los AirPods Max; reinventan los audífonos de diadema. El controlador dinámico diseñado por Apple te ofrece un sonido inmersivo de alta fidelidad. Cada elemento, desde la diadema hasta las almohadillas, está pensado para brindarte un ajuste excepcional. La Cancelación Activa de Ruido líder en la industria bloquea el ruido exterior, y el modo Ambiente te permite escuchar todo lo que ocurre a tu alrededor.  Conectividad: Inalámbrico.    Caracteristicas: Cancelación del ruido, Circumaurales, Con batería recargable, Con efecto de graves, Con estuche de carga, Con micrófono, Sonido envolvente.    Tipo de auricular: Abierto Tecnología del controlador de los auriculares: Dinámico", 
        "numerodecantidades": 10,
        "tallaInicial":  0,
        "tallaFinal": 0 
    },
    {
        "id": "reloj-01",
        "titulo": "FOSSIL U.S.A.",
        "imagen":["./images/relojes/2.jpg", "./images/relojes/2.1.jpg", "./images/relojes/2.2.jpg", "./images/relojes/2.3.jpg","./images/relojes/2.4.jpg", "./images/relojes/2.5.jpg", "./images/relojes/2.6.jpg", "./images/relojes/2.7.jpg", "./images/relojes/2.8.jpg", "./images/relojes/2.9.jpg"],
        "categoria": {
            "nombre":  "FOSSIL U.S.A.",
            "id": "electronico"
        },
        "precio": 48000,
        "colores": ["reloj blanco con azul", "reloj negro con tonos dorados", "reloj azul con tonos dorados", "relog negro con tonos plateados", "reloj negro con blanco"],
        "info" : "▪ Reloj De Nueva Colección Con Calendario Y Segundero Funcional, Cristal En Mineral Y Pulso Acerado,          ▪ Adquiere El Estuche De Lujo Contramarcado Por $12.000", 
        "numerodecantidades": 10,
        "tallaInicial":  0,
        "tallaFinal": 0
    },
    {
        "id": "reloj-02",
        "titulo": "CASIO 2024 Model",
        "imagen":["./images/relojes/1.jpg", "./images/relojes/1.1.jpg", "./images/relojes/1.2.jpg", "./images/relojes/1.3.jpg","./images/relojes/1.4.jpg"],
        "categoria": {
            "nombre":  "CASIO 2024 Model",
            "id": "electronico"
        },
        "precio": 65000,
        "colores": ["dorado", "dorado con blanco", "dorado con azul y blanco", "blanco", "blanco con negro"],
        "info" : "Reloj Gama Alta Con Múltiples Funciones: Doble Hora, Fecha, Cronómetro, Alarma Y Luz; Pulso Acerado , RESISTENTE AL AGUA", 
        "numerodecantidades": 10,
        "tallaInicial":  0,
        "tallaFinal": 0 
    }













    
   
]
